odoo/addons/res_partner_industry_multi_company/README.rst
odoo/addons/res_partner_industry_multi_company/__init__.py
odoo/addons/res_partner_industry_multi_company/__manifest__.py
odoo/addons/res_partner_industry_multi_company/i18n/it.po
odoo/addons/res_partner_industry_multi_company/i18n/res_partner_industry_multi_company.pot
odoo/addons/res_partner_industry_multi_company/models/__init__.py
odoo/addons/res_partner_industry_multi_company/models/res_partner_industry.py
odoo/addons/res_partner_industry_multi_company/readme/CONTRIBUTORS.md
odoo/addons/res_partner_industry_multi_company/readme/DESCRIPTION.md
odoo/addons/res_partner_industry_multi_company/security/res_partner_industry.xml
odoo/addons/res_partner_industry_multi_company/static/description/icon.png
odoo/addons/res_partner_industry_multi_company/static/description/index.html
odoo/addons/res_partner_industry_multi_company/views/res_partner_industry.xml
odoo_addon_res_partner_industry_multi_company-18.0.1.0.1.4.dist-info/METADATA
odoo_addon_res_partner_industry_multi_company-18.0.1.0.1.4.dist-info/WHEEL
odoo_addon_res_partner_industry_multi_company-18.0.1.0.1.4.dist-info/top_level.txt
odoo_addon_res_partner_industry_multi_company-18.0.1.0.1.4.dist-info/RECORD
