Metadata-Version: 2.1
Name: odoo-addon-res_partner_industry_multi_company
Version: 18.0.1.0.1.4
Requires-Python: >=3.10
Requires-Dist: odoo==18.0.*
Summary: This module add multi-company management to res partner industry
Home-page: https://github.com/OCA/multi-company
License: AGPL-3
Author: ACSONE SA/NV,Odoo Community Association (OCA)
Author-email: support@odoo-community.org
Classifier: Programming Language :: Python
Classifier: Framework :: Odoo
Classifier: Framework :: Odoo :: 18.0
Classifier: License :: OSI Approved :: GNU Affero General Public License v3
